cnab/__init__.py
cnab/cnab.py
cnab/invocation_image.py
cnab/test_cnab.py
cnab/test_invocation_image.py
cnab/test_types.py
cnab/test_util.py
cnab/types.py
cnab/util.py
cnab-0.1.7.dist-info/LICENSE
cnab-0.1.7.dist-info/WHEEL
cnab-0.1.7.dist-info/METADATA
cnab-0.1.7.dist-info/RECORD
